MANIFEST.in
ez_setup.py
setup.py
pyradar/__init__.py
pyradar.egg-info/PKG-INFO
pyradar.egg-info/SOURCES.txt
pyradar.egg-info/dependency_links.txt
pyradar.egg-info/requires.txt
pyradar.egg-info/top_level.txt
pyradar/classifiers/__init__.py
pyradar/classifiers/isodata.py
pyradar/classifiers/kmeans.py
pyradar/comparator/__init__.py
pyradar/comparator/comparator_utils.py
pyradar/comparator/image_comparator.py
pyradar/core/__init__.py
pyradar/core/equalizers.py
pyradar/core/sar.py
pyradar/filters/__init__.py
pyradar/filters/frost.py
pyradar/filters/kuan.py
pyradar/filters/lee.py
pyradar/filters/lee_enhanced.py
pyradar/filters/mean.py
pyradar/filters/median.py
pyradar/filters/utils.py
pyradar/simulate/__init__.py
pyradar/simulate/image_simulator.py
pyradar/simulate/ExampleImages/demo_K.png
pyradar/simulate/ExampleImages/demo_gamma.png
pyradar/simulate/ExampleImages/DemoSet/gamma_img_layer.png
pyradar/simulate/ExampleImages/DemoSet/gamma_noisy_img.png
pyradar/simulate/ExampleImages/DemoSet/k_img_layer.png
pyradar/simulate/ExampleImages/DemoSet/k_noisy_img.png
pyradar/utils/__init__.py
pyradar/utils/sar_debugger.py
pyradar/utils/statutils.py
pyradar/utils/system_info.py
pyradar/utils/timeutils.py