Metadata-Version: 1.1
Name: pyradar
Version: 0.2
Summary: Collection of algortihms and tools for manipulate satellite images
Home-page: https://github.com/PyRadar/pyradar
Author: Matías Herranz <matiasherranz@gmail.com> - Joaquín Tita <joaquintita@gmail.com>
Author-email: matiasherranz@gmail.com - joaquintita@gmail.com
License: LGPL 3
Keywords: radar satellite image sar lee kuan lee-enhanced
Platform: UNKNOWN
Classifier: Programming Language :: Python :: 2
Classifier: Intended Audience :: Science/Research
Classifier: License :: OSI Approved :: GNU Lesser General Public License v3 or later (LGPLv3+)
Classifier: Topic :: Multimedia :: Graphics
Classifier: Topic :: Scientific/Engineering :: Image Recognition
Classifier: Topic :: Utilities
